{
  "source": "NASA FIRMS VIIRS NOAA-20 C2 (24h)",
  "source_url": "https://firms.modaps.eosdis.nasa.gov/",
  "description": "Active wildfires in the Colorado River Basin (31-42\u00b0N, 107-115\u00b0W), last 24 hours",
  "coverage_bbox": {
    "min_lat": 31,
    "max_lat": 42,
    "min_lon": -115,
    "max_lon": -107
  },
  "last_updated": "2026-07-18T04:39:45.743580+00:00",
  "fire_count": 36,
  "fires": [
    {
      "latitude": 39.88922,
      "longitude": -108.23866,
      "brightness": 303.16,
      "frp": 2.2,
      "confidence": "nominal",
      "acq_date": "2026-07-16",
      "acq_time": "0826",
      "satellite": "N20"
    },
    {
      "latitude": 39.88391,
      "longitude": -108.23938,
      "brightness": 328.24,
      "frp": 2.2,
      "confidence": "nominal",
      "acq_date": "2026-07-16",
      "acq_time": "0826",
      "satellite": "N20"
    },
    {
      "latitude": 39.8844,
      "longitude": -108.2485,
      "brightness": 309.78,
      "frp": 2.11,
      "confidence": "nominal",
      "acq_date": "2026-07-16",
      "acq_time": "0826",
      "satellite": "N20"
    },
    {
      "latitude": 39.88415,
      "longitude": -108.24387,
      "brightness": 312.12,
      "frp": 2.2,
      "confidence": "nominal",
      "acq_date": "2026-07-16",
      "acq_time": "0826",
      "satellite": "N20"
    },
    {
      "latitude": 39.88366,
      "longitude": -108.23488,
      "brightness": 316.92,
      "frp": 3.07,
      "confidence": "nominal",
      "acq_date": "2026-07-16",
      "acq_time": "0826",
      "satellite": "N20"
    },
    {
      "latitude": 39.87861,
      "longitude": -108.24026,
      "brightness": 300.15,
      "frp": 1.48,
      "confidence": "nominal",
      "acq_date": "2026-07-16",
      "acq_time": "0826",
      "satellite": "N20"
    },
    {
      "latitude": 39.87837,
      "longitude": -108.23586,
      "brightness": 303.29,
      "frp": 1.41,
      "confidence": "nominal",
      "acq_date": "2026-07-16",
      "acq_time": "0826",
      "satellite": "N20"
    },
    {
      "latitude": 39.86827,
      "longitude": -108.24705,
      "brightness": 299.29,
      "frp": 0.67,
      "confidence": "nominal",
      "acq_date": "2026-07-16",
      "acq_time": "0826",
      "satellite": "N20"
    },
    {
      "latitude": 39.86803,
      "longitude": -108.24238,
      "brightness": 299.01,
      "frp": 0.67,
      "confidence": "nominal",
      "acq_date": "2026-07-16",
      "acq_time": "0826",
      "satellite": "N20"
    },
    {
      "latitude": 39.86982,
      "longitude": -108.2441,
      "brightness": 305.58,
      "frp": 1.62,
      "confidence": "nominal",
      "acq_date": "2026-07-16",
      "acq_time": "0826",
      "satellite": "N20"
    },
    {
      "latitude": 38.95158,
      "longitude": -107.49748,
      "brightness": 297.01,
      "frp": 0.45,
      "confidence": "nominal",
      "acq_date": "2026-07-16",
      "acq_time": "0826",
      "satellite": "N20"
    },
    {
      "latitude": 38.20382,
      "longitude": -107.54041,
      "brightness": 300.03,
      "frp": 1.04,
      "confidence": "nominal",
      "acq_date": "2026-07-16",
      "acq_time": "0826",
      "satellite": "N20"
    },
    {
      "latitude": 38.19097,
      "longitude": -107.50119,
      "brightness": 301.39,
      "frp": 0.84,
      "confidence": "nominal",
      "acq_date": "2026-07-16",
      "acq_time": "0826",
      "satellite": "N20"
    },
    {
      "latitude": 38.19073,
      "longitude": -107.4978,
      "brightness": 297.81,
      "frp": 0.84,
      "confidence": "nominal",
      "acq_date": "2026-07-16",
      "acq_time": "0826",
      "satellite": "N20"
    },
    {
      "latitude": 38.18745,
      "longitude": -107.52355,
      "brightness": 327.97,
      "frp": 3.23,
      "confidence": "nominal",
      "acq_date": "2026-07-16",
      "acq_time": "0826",
      "satellite": "N20"
    },
    {
      "latitude": 38.18765,
      "longitude": -107.52638,
      "brightness": 314.07,
      "frp": 1.86,
      "confidence": "nominal",
      "acq_date": "2026-07-16",
      "acq_time": "0826",
      "satellite": "N20"
    },
    {
      "latitude": 38.18586,
      "longitude": -107.50037,
      "brightness": 307.47,
      "frp": 0.91,
      "confidence": "nominal",
      "acq_date": "2026-07-16",
      "acq_time": "0826",
      "satellite": "N20"
    },
    {
      "latitude": 38.18565,
      "longitude": -107.49737,
      "brightness": 299.15,
      "frp": 0.91,
      "confidence": "nominal",
      "acq_date": "2026-07-16",
      "acq_time": "0826",
      "satellite": "N20"
    },
    {
      "latitude": 38.18261,
      "longitude": -107.52677,
      "brightness": 299.74,
      "frp": 1.86,
      "confidence": "nominal",
      "acq_date": "2026-07-16",
      "acq_time": "0826",
      "satellite": "N20"
    },
    {
      "latitude": 38.18077,
      "longitude": -107.49989,
      "brightness": 301.69,
      "frp": 0.91,
      "confidence": "nominal",
      "acq_date": "2026-07-16",
      "acq_time": "0826",
      "satellite": "N20"
    },
    {
      "latitude": 38.17737,
      "longitude": -107.52435,
      "brightness": 298.91,
      "frp": 1.11,
      "confidence": "nominal",
      "acq_date": "2026-07-16",
      "acq_time": "0826",
      "satellite": "N20"
    },
    {
      "latitude": 38.17268,
      "longitude": -107.52978,
      "brightness": 302.54,
      "frp": 1.22,
      "confidence": "nominal",
      "acq_date": "2026-07-16",
      "acq_time": "0826",
      "satellite": "N20"
    },
    {
      "latitude": 38.1725,
      "longitude": -107.52717,
      "brightness": 306.74,
      "frp": 1.22,
      "confidence": "nominal",
      "acq_date": "2026-07-16",
      "acq_time": "0826",
      "satellite": "N20"
    },
    {
      "latitude": 38.17232,
      "longitude": -107.52452,
      "brightness": 308.65,
      "frp": 1.11,
      "confidence": "nominal",
      "acq_date": "2026-07-16",
      "acq_time": "0826",
      "satellite": "N20"
    },
    {
      "latitude": 38.16748,
      "longitude": -107.52773,
      "brightness": 328.56,
      "frp": 2.68,
      "confidence": "nominal",
      "acq_date": "2026-07-16",
      "acq_time": "0826",
      "satellite": "N20"
    },
    {
      "latitude": 38.16729,
      "longitude": -107.525,
      "brightness": 322.8,
      "frp": 3.62,
      "confidence": "nominal",
      "acq_date": "2026-07-16",
      "acq_time": "0826",
      "satellite": "N20"
    },
    {
      "latitude": 38.16765,
      "longitude": -107.53034,
      "brightness": 311.43,
      "frp": 2.68,
      "confidence": "nominal",
      "acq_date": "2026-07-16",
      "acq_time": "0826",
      "satellite": "N20"
    },
    {
      "latitude": 39.37634,
      "longitude": -109.16334,
      "brightness": 351.57,
      "frp": 23.7,
      "confidence": "nominal",
      "acq_date": "2026-07-16",
      "acq_time": "1947",
      "satellite": "N20"
    },
    {
      "latitude": 38.09876,
      "longitude": -107.32898,
      "brightness": 335.43,
      "frp": 9.77,
      "confidence": "low",
      "acq_date": "2026-07-16",
      "acq_time": "1949",
      "satellite": "N20"
    },
    {
      "latitude": 38.12551,
      "longitude": -107.3183,
      "brightness": 337.07,
      "frp": 10.32,
      "confidence": "nominal",
      "acq_date": "2026-07-16",
      "acq_time": "1949",
      "satellite": "N20"
    },
    {
      "latitude": 38.19375,
      "longitude": -107.52518,
      "brightness": 303.18,
      "frp": 3.6,
      "confidence": "nominal",
      "acq_date": "2026-07-17",
      "acq_time": "0807",
      "satellite": "N20"
    },
    {
      "latitude": 38.19357,
      "longitude": -107.52438,
      "brightness": 306.43,
      "frp": 3.38,
      "confidence": "nominal",
      "acq_date": "2026-07-17",
      "acq_time": "0807",
      "satellite": "N20"
    },
    {
      "latitude": 38.93864,
      "longitude": -112.81401,
      "brightness": 306.63,
      "frp": 1.21,
      "confidence": "nominal",
      "acq_date": "2026-07-17",
      "acq_time": "0947",
      "satellite": "N20"
    },
    {
      "latitude": 32.06052,
      "longitude": -109.89423,
      "brightness": 296.83,
      "frp": 0.58,
      "confidence": "nominal",
      "acq_date": "2026-07-17",
      "acq_time": "0949",
      "satellite": "N20"
    },
    {
      "latitude": 40.18639,
      "longitude": -111.8998,
      "brightness": 330.42,
      "frp": 9.83,
      "confidence": "low",
      "acq_date": "2026-07-17",
      "acq_time": "2110",
      "satellite": "N20"
    },
    {
      "latitude": 41.88514,
      "longitude": -110.08702,
      "brightness": 346.21,
      "frp": 12.27,
      "confidence": "nominal",
      "acq_date": "2026-07-17",
      "acq_time": "2110",
      "satellite": "N20"
    }
  ]
}